<annotation>
	<folder>Images</folder>
	<filename>207.jpg</filename>
	<path>D:\pycodes\windows_labelimg\Images\207.jpg</path>
	<source>
		<database>Unknown</database>
	</source>
	<size>
		<width>1920</width>
		<height>1080</height>
		<depth>3</depth>
	</size>
	<segmented>0</segmented>
	<object>
		<name>red_cone</name>
		<pose>Unspecified</pose>
		<truncated>0</truncated>
		<difficult>0</difficult>
		<bndbox>
			<xmin>603</xmin>
			<ymin>421</ymin>
			<xmax>699</xmax>
			<ymax>527</ymax>
		</bndbox>
	</object>
	<object>
		<name>red_cone</name>
		<pose>Unspecified</pose>
		<truncated>0</truncated>
		<difficult>0</difficult>
		<bndbox>
			<xmin>1357</xmin>
			<ymin>316</ymin>
			<xmax>1405</xmax>
			<ymax>366</ymax>
		</bndbox>
	</object>
	<object>
		<name>red_cone</name>
		<pose>Unspecified</pose>
		<truncated>0</truncated>
		<difficult>0</difficult>
		<bndbox>
			<xmin>1164</xmin>
			<ymin>329</ymin>
			<xmax>1201</xmax>
			<ymax>392</ymax>
		</bndbox>
	</object>
	<object>
		<name>red_cone</name>
		<pose>Unspecified</pose>
		<truncated>0</truncated>
		<difficult>0</difficult>
		<bndbox>
			<xmin>1638</xmin>
			<ymin>327</ymin>
			<xmax>1670</xmax>
			<ymax>388</ymax>
		</bndbox>
	</object>
	<object>
		<name>red_cone</name>
		<pose>Unspecified</pose>
		<truncated>0</truncated>
		<difficult>0</difficult>
		<bndbox>
			<xmin>1862</xmin>
			<ymin>340</ymin>
			<xmax>1888</xmax>
			<ymax>397</ymax>
		</bndbox>
	</object>
	<object>
		<name>blue_cone</name>
		<pose>Unspecified</pose>
		<truncated>0</truncated>
		<difficult>0</difficult>
		<bndbox>
			<xmin>1727</xmin>
			<ymin>488</ymin>
			<xmax>1814</xmax>
			<ymax>616</ymax>
		</bndbox>
	</object>
	<object>
		<name>blue_cone</name>
		<pose>Unspecified</pose>
		<truncated>1</truncated>
		<difficult>0</difficult>
		<bndbox>
			<xmin>1873</xmin>
			<ymin>421</ymin>
			<xmax>1920</xmax>
			<ymax>488</ymax>
		</bndbox>
	</object>
</annotation>
